djin/__init__.py
djin-0.0.1.dist-info/METADATA
djin-0.0.1.dist-info/WHEEL
djin-0.0.1.dist-info/RECORD
